README.md
__init__.py
meausre.py
setup.py
spellcor.py
spellcor_utils.py
spellcor.egg-info/PKG-INFO
spellcor.egg-info/SOURCES.txt
spellcor.egg-info/dependency_links.txt
spellcor.egg-info/not-zip-safe
spellcor.egg-info/top_level.txt
spellcor_models/__init__.py
spellcor_models/languageModel.py
spellcor_models/nglm.py